{
  "openapi": "3.0.0",
  "info": {
    "title": "NETPIPO BACKEND API DOCUMENTATION",
    "description": "Documentation for the Express API endpoints",
    "version": "1.0.0"
  },
  "servers": [
    {
      "url": "https://netpipobackend-gwa8.onrender.com/"
    }
  ],
  "paths": {
    "/employees/signUp": {
      "post": {
        "tags": ["employee"],
        "description": "",
        "responses": {
          "200": {
            "description": "OK"
          },
          "400": {
            "description": "Bad Request"
          }
        },
        "requestBody": {
          "content": {
            "application/json": {
              "schema": {
                "type": "object",
                "properties": {
                  "firstname": {
                    "example": "any"
                  },
                  "lastname": {
                    "example": "any"
                  },
                  "employeename": {
                    "example": "any"
                  },
                  "email": {
                    "example": "any"
                  },
                  "password": {
                    "example": "any"
                  }
                }
              }
            }
          }
        }
      }
    },
    "/employees/signIn": {
      "post": {
        "tags": ["employee"],
        "description": "",
        "responses": {
          "200": {
            "description": "OK"
          },
          "401": {
            "description": "Unauthorized"
          }
        },
        "requestBody": {
          "content": {
            "application/json": {
              "schema": {
                "type": "object",
                "properties": {
                  "email": {
                    "example": "any"
                  },
                  "password": {
                    "example": "any"
                  }
                }
              }
            }
          }
        }
      }
    },
    "/employees/all": {
      "get": {
        "tags": ["employee"],
        "description": "",
        "responses": {
          "200": {
            "description": "OK"
          },
          "500": {
            "description": "Internal Server Error"
          }
        }
      }
    },
    "/employees/single/{id}": {
      "get": {
        "tags": ["employee"],
        "description": "",
        "parameters": [
          {
            "name": "id",
            "in": "path",
            "required": true,
            "schema": {
              "type": "string"
            }
          }
        ],
        "responses": {
          "200": {
            "description": "OK"
          },
          "404": {
            "description": "Not Found"
          }
        }
      }
    },
    "/employees/update/{id}": {
      "put": {
        "tags": ["employee"],
        "description": "",
        "parameters": [
          {
            "name": "id",
            "in": "path",
            "required": true,
            "schema": {
              "type": "string"
            }
          }
        ],
        "responses": {
          "200": {
            "description": "OK"
          },
          "400": {
            "description": "Bad Request"
          },
          "404": {
            "description": "Not Found"
          }
        },
        "requestBody": {
          "content": {
            "application/json": {
              "schema": {
                "type": "object",
                "properties": {
                  "firstname": {
                    "example": "any"
                  },
                  "lastname": {
                    "example": "any"
                  },
                  "employeename": {
                    "example": "any"
                  },
                  "email": {
                    "example": "any"
                  },
                  "password": {
                    "example": "any"
                  }
                }
              }
            }
          }
        }
      }
    },
    "/employees/delete/{id}": {
      "delete": {
        "tags": ["employee"],
        "description": "",
        "parameters": [
          {
            "name": "id",
            "in": "path",
            "required": true,
            "schema": {
              "type": "string"
            }
          }
        ],
        "responses": {
          "200": {
            "description": "OK"
          },
          "404": {
            "description": "Not Found"
          }
        }
      }
    },
    "/employees/deleteAll": {
      "delete": {
        "tags": ["employee"],
        "description": "",
        "responses": {
          "200": {
            "description": "OK"
          }
        }
      }
    }
  },
  "components": {
    "securitySchemes": {
      "bearerAuth": {
        "type": "http",
        "scheme": "bearer"
      }
    }
  }
}
